{
  "couple": {
    "groom": {
      "name": "Reysen Solivio Flores"
    },
    "bride": {
      "name": "Danna Rose Quizo Obordo"
    }
  },
  "parents": {
    "groom": {
      "father": "Rolando T. Flores, Jr.",
      "mother": "Cresilda S. Flores"
    },
    "bride": {
      "father": "Peter Paul P. Obordo",
      "mother": "Helen Q. Obordo"
    }
  },
  "entourageList": [
    {
      "category": "Principal Sponsors",
      "ninong": [
        "Mr. Peter Arcete",
        "Mr. Paul Boligao",
        "Mr. Victor Operario Jr.",
        "Mr. Victor Obordo",
        "Mr. Albert Aniñon",
        "Mr. Souvenir Hope Osorio",
        "Mr. Decoroso Elumbaring",
        "Mr. Joel Lomocso",
        "Mr. Ryian P. Benitez",
        "Mr. Joseph Faith M. Borlaza",
        "Mr. Mark Y. Ramirez",
        "Mr. Philips F. Adasa",
        "Mr. Vincent Tanjay",
        "Mr. Nimuel J. Diagmel",
        "Mr. Celso V. Marquez",
        "Mr. Roy V. Bacon",
        "Mr. Jervy M. Labores"
      ],
      "ninang": [
        "Mrs. Michelle Arcete",
        "Mrs. Mercy Boligao",
        "Mrs. Maria Elvie Operario",
        "Mrs. Sarah Obordo",
        "Mrs. Arceli Palmero",
        "Mrs. Irish Mae T. Osorio",
        "Mrs. Charmaine I. Elumbaring",
        "Mrs. Melanie P. Lomocso",
        "Mrs. Lily P. Benitez",
        "Mrs. Maribeth A. Borlaza",
        "Mrs. Betsy Q. Ramirez",
        "Ms. Christine C. Andus",
        "Mrs. Zeneth F. Tanjay",
        "Mrs. Haidee O. Diagmel",
        "Mrs. Georgee V. Marquez",
        "Mrs. Ester D. Bacon",
        "Mrs. Christine Joy S. Labores"
      ]
    },
    {
      "category": "Bestman",
      "names": [
        "Rolando T. Flores III"
      ]
    },
    {
      "category": "Maid of Honor",
      "names": [
        "Jessca Marie Obordo-Dulang"
      ]
    },
    {
      "category": "Secondary Sponsors",
      "groomsmen": [
        "Zedley Laput",
        "Chivy John Enguito",
        "John Francis F. Colcol",
        "Joshue F. Requina",
        "Bobby S. Dumadag",
        "Jericho L. Villaroman",
        "Jan-riel P. Flores",
        "Roland Sebastian F. Colcol"
      ],
      "bridesmaid": [
        "Mary Ryavienne Lexi A. Obordo",
        "Adriel Eunice Obordo",
        "Edcel Marie Laput",
        "Herlyn Laput",
        "Jinky Marie Quizo",
        "Shaneia Kane Q. Sanoy",
        "Kea Mae D. Solivio",
        "Merlycar D. Solivio",
        "Kristine S. Flores",
        "Jashley Jaye F. Acas",
        "Charlene Tagantan",
        "Rishaynne khaye A. Flores"
      ]
    },
    {
      "category": "Candle Sponsors",
      "names": [
        "Mr. Rolando S. Flores III",
        "Mrs. Eva May T. Flores"
      ]
    },
    {
      "category": "Veil Sponsors",
      "names": [
        "Mr. Christian Roy Dulang",
        "Mrs. Jessca Marie Obordo-Dulang"
      ]
    },
    {
      "category": "Cord Sponsors",
      "names": [
        "Mr. Otto Von L. Borbon",
        "Mrs. Jomarie B. Borbon"
      ]
    },
    {
      "category": "Ring Bearer",
      "names": [
        "Kaleb L. Borbon"
      ]
    },
    {
      "category": "Coin Bearer",
      "names": [
        "Rhainer A. Flores"
      ]
    },
    {
      "category": "Bible Bearer",
      "names": [
        "Lance T. Flores"
      ]
    },
    {
      "category": "Flower Boys",
      "names": [
        "Khalil Laput",
        "Donie P. Flores",
        "Nicklaus C. Solivio"
      ]
    },
    {
      "category": "Junior Flower Girls",
      "names": [
        "Dayne Solivio",
        "Fern Marguerith O. Dulang",
        "Keona L. Borbon",
        "Dulce Amarys R. Bajamunde",
        "Ariana P. Flores",
        "Scarlette Summer M. Solivio"
      ]
    }
  ]
}
